[
    {
        "name": "id",
        "dbType": "integer,true",
        "htmlType": "number",
        "validations": "",
        "searchable": false,
        "fillable": false,
        "primary": true,
        "inForm": false,
        "inIndex": false,
        "inView": false
    },
    {
        "name": "name",
        "dbType": "string",
        "htmlType": "text",
        "validations": "required|string|string|string",
        "searchable": true,
        "fillable": true,
        "primary": false,
        "inForm": true,
        "inIndex": true,
        "inView": true
    },
    {
        "name": "variable_id",
        "dbType": "bigInteger,false",
        "htmlType": "number",
        "validations": "nullable|nullable|nullable",
        "searchable": true,
        "fillable": true,
        "primary": false,
        "inForm": true,
        "inIndex": true,
        "inView": true
    },
    {
        "name": "created_at",
        "dbType": "datetime",
        "htmlType": "date",
        "validations": "required",
        "searchable": false,
        "fillable": false,
        "primary": false,
        "inForm": false,
        "inIndex": false,
        "inView": false
    },
    {
        "name": "updated_at",
        "dbType": "dateTimeTz",
        "htmlType": "date",
        "validations": "nullable|nullable|nullable",
        "searchable": false,
        "fillable": false,
        "primary": false,
        "inForm": false,
        "inIndex": false,
        "inView": false
    },
    {
        "name": "deleted_at",
        "dbType": "datetime",
        "htmlType": "date",
        "validations": "nullable|nullable|nullable",
        "searchable": false,
        "fillable": false,
        "primary": false,
        "inForm": false,
        "inIndex": false,
        "inView": false
    },
    {
        "name": "number_of_conditions",
        "dbType": "bigInteger,false",
        "htmlType": "number",
        "validations": "nullable|nullable|nullable",
        "searchable": true,
        "fillable": true,
        "primary": false,
        "inForm": true,
        "inIndex": true,
        "inView": true
    },
    {
        "name": "_airbyte_ab_id",
        "dbType": "string",
        "htmlType": "text",
        "validations": "nullable|string|nullable|string|nullable|string",
        "searchable": true,
        "fillable": true,
        "primary": false,
        "inForm": true,
        "inIndex": true,
        "inView": true
    },
    {
        "name": "_airbyte_emitted_at",
        "dbType": "dateTimeTz",
        "htmlType": "date",
        "validations": "nullable|nullable|nullable",
        "searchable": true,
        "fillable": true,
        "primary": false,
        "inForm": true,
        "inIndex": true,
        "inView": true
    },
    {
        "name": "_airbyte_normalized_at",
        "dbType": "dateTimeTz",
        "htmlType": "date",
        "validations": "nullable|nullable|nullable",
        "searchable": true,
        "fillable": true,
        "primary": false,
        "inForm": true,
        "inIndex": true,
        "inView": true
    },
    {
        "name": "_airbyte_ct_causes_hashid",
        "dbType": "text",
        "htmlType": "textarea",
        "validations": "nullable|string|nullable|string|nullable|string",
        "searchable": true,
        "fillable": true,
        "primary": false,
        "inForm": true,
        "inIndex": true,
        "inView": true
    },
    {
        "type": "relation",
        "relation": "mt1,Variable,variable_id"
    },
    {
        "type": "relation",
        "relation": "1tm,CtConditionCause,cause_id"
    }
]